{
  "quizzes": {
    "dva1501": {
        "title": "DVA1501"
      },
      "pls1501": {
        "title": "PLS1501"
      },
      "pyc1511": {
        "title": "PYC1511"
      },
      "pyc1512": {
        "title": "PYC1512"
      },
      "pyc1513": {
        "title": "PYC1513"
      },
      "ediblevtoxic": {
        "title": "MYC1001"
      }
  },
  "buttonLabels": {
    "startQuiz": "Start Quiz",
    "revealAnswer": "✨ Reveal Answer",
    "nextQuestion": "⏭ Next Question",
    "pauseQuiz": "⏸ Pause"
  },
  "textDefaults": {
    "titleText": "TRAP.LOL | Quiz'z",
    "loadingText": "Preparing quiz...",
    "returnHome": "🏠",
    "restartQuiz": "🔄",
    "numberOfQuestions": "Number of Questions",
    "autoplayQuestions": "Auto-play Questions",
    "infiniteQuestions": "Infinite",
    "infiniteSymbol": "∞"
  },
  "errorMessages": {
    "loadQuestions": "Failed to load questions",
    "loadLocalization": "Failed to load translations"
  }
}